{"NOT": 2, "ROFL": 1, "TV": 5, "XMR": 7, "BUY": 13, "GUI": 1, "CLI": 1, "US": 13, "EU": 3, "UK": 1, "DE": 1, "WOEVY": 1, "BBBYQ": 7, "BBBY": 12, "DK": 2, "RC": 3, "IP": 1, "GME": 11, "CUSIP": 2, "NW": 1, "BTC": 16, "XSG": 2, "XRP": 5, "XRPL": 3, "FUD": 3, "BINGO": 1, "ANTI": 1, "CENT": 1, "ITS": 1, "GONNA": 1, "POP": 1, "JFC": 1, "OIL": 1, "WERE": 1, "THIS": 3, "THE": 9, "END": 1, "OF": 4, "HIPE": 1, "ICP": 3, "SPCE": 2, "MSTR": 1, "WHERE": 3, "FUCK": 3, "ARE": 2, "GG": 1, "IT": 2, "DOESN": 2, "NOW": 2, "WHAT": 5, "WILL": 4, "NEVER": 2, "GIVE": 4, "UP": 1, "FIGHT": 1, "THERE": 3, "IS": 9, "NO": 4, "WAY": 2, "RUN": 1, "AWAY": 1, "FROM": 5, "ALL": 4, "MY": 2, "LONG": 1, "AS": 1, "VOICE": 1, "ME": 7, "SAYS": 1, "KEEP": 1, "ON": 2, "TO": 41, "STOP": 2, "GOIN": 1, "VERY": 1, "TOP": 1, "WHO": 2, "WRONG": 2, "OR": 1, "RIGHT": 2, "WTF": 1, "LINK": 3, "GDP": 1, "CPI": 1, "EBAY": 3, "WE": 2, "CAN": 3, "GO": 1, "BOOM": 1, "BUST": 1, "BOWL": 1, "DUST": 1, "FALL": 1, "RED": 1, "GLARE": 1, "DOWN": 1, "YOU": 6, "SPARE": 1, "WAR": 1, "AND": 4, "LOST": 1, "PISS": 1, "SHIT": 1, "WT": 1, "DOGE": 1, "HOLY": 1, "QNT": 1, "INTJ": 1, "SACH": 1, "BTFO": 1, "VOO": 1, "OOOO": 1, "GTFO": 1, "USA": 1, "CME": 2, "MUST": 1, "ASTER": 1, "NVDA": 1, "ICX": 1, "TOLD": 1, "SO": 2, "KEK": 1, "LITS": 1, "MFW": 1, "HOA": 1, "SFH": 1, "WALLS": 1, "JUAN": 1, "WITH": 1, "TIME": 30, "AINT": 1, "RAPE": 1, "TRAIN": 1, "CKB": 1, "HA": 1, "YOUR": 3, "PILLS": 1, "MAKE": 1, "ILL": 1, "RE": 1, "AFTER": 1, "THAT": 1, "LL": 1, "KILL": 1, "IF": 1, "WANT": 1, "THEN": 1, "FIRE": 1, "AT": 1, "DTCC": 1, "FDIC": 1, "DRS": 1, "DSPP": 1, "HF": 1, "ITM": 1, "HAVE": 1, "BEEN": 1, "DUPED": 1, "BY": 1, "CANT": 1, "SIX": 1, "SEVEN": 1, "SLURP": 7, "AHHH": 1, "IMHZ": 1, "GRGGD": 1, "LERP": 1, "IDZ": 1, "GORW": 1, "AHHHH": 1, "AHH": 1}